kaiba_cli/__init__.py
kaiba_cli/cli.py
kaiba_cli/common.py
kaiba_cli-0.2.1.dist-info/entry_points.txt
kaiba_cli-0.2.1.dist-info/LICENSE
kaiba_cli-0.2.1.dist-info/WHEEL
kaiba_cli-0.2.1.dist-info/METADATA
kaiba_cli-0.2.1.dist-info/RECORD
